mathtools/__init__.py
mathtools/math.py
anasxon_math-1.0.0.dist-info/METADATA
anasxon_math-1.0.0.dist-info/WHEEL
anasxon_math-1.0.0.dist-info/top_level.txt
anasxon_math-1.0.0.dist-info/RECORD
