Metadata-Version: 2.4
Name: anasxon_math
Version: 1.0.0
Summary: A collection of mathematical tools and utilities
Author: Anasxon Ummataliy
License: MIT
Requires-Python: >=3.6
Requires-Dist: numpy>=1.18.0
Dynamic: author
Dynamic: description
Dynamic: description-content-type
Dynamic: license
Dynamic: requires-dist
Dynamic: requires-python
Dynamic: summary
